neolixir/__init__.py
neolixir/batch.py
neolixir/dummy.py
neolixir/entity.py
neolixir/exc.py
neolixir/fast.py
neolixir/index.py
neolixir/metadata.py
neolixir/node.py
neolixir/observable.py
neolixir/overrides.py
neolixir/properties.py
neolixir/propmap.py
neolixir/query.py
neolixir/relationship.py
neolixir/relmap.py
neolixir/session.py
neolixir/utils.py
neolixir-2.1.3.dist-info/DESCRIPTION.rst
neolixir-2.1.3.dist-info/METADATA
neolixir-2.1.3.dist-info/RECORD
neolixir-2.1.3.dist-info/WHEEL
neolixir-2.1.3.dist-info/metadata.json
neolixir-2.1.3.dist-info/top_level.txt
