Metadata-Version: 2.0
Name: neolixir
Version: 2.1.3
Summary: A declarative ORM abstraction layer for Neo4j
Home-page: http://neolixir.org
Author: Ivo Tzvetkov
Author-email: ivotkv@gmail.com
License: MIT
Download-URL: https://github.com/ivotkv/neolixir/tarball/v2.1.3
Keywords: neo4j,declarative,orm,polymorphic,schema,session
Platform: UNKNOWN
Classifier: Development Status :: 5 - Production/Stable
Classifier: Intended Audience :: Developers
Classifier: License :: OSI Approved :: MIT License
Classifier: Operating System :: OS Independent
Classifier: Programming Language :: Python :: 2.7
Classifier: Topic :: Database
Classifier: Topic :: Software Development
Requires-Dist: py2neo (<2.1,>=2.0)
Requires-Dist: simplejson
